{"name":"Flute","presetId":73,"bankId":0,"pbagIndex":1261,"misc":[0,0,0],"zones":[{"sampleOffsets":[-1,-1,-1,-1],"velRange":{"lo":99,"hi":127},"keyRange":{"lo":0,"hi":63},"generators":[],"sample":{"name":"Flute-C#4","start":2494413,"end":2524384,"startLoop":2511835,"endLoop":2524051,"sampleRate":32000,"originalPitch":60,"pitchCorrection":0,"sampleLink":0,"sampleType":1},"adsr":[-12000,-12000,1000,-12000]},{"sampleOffsets":[-1,-1,-1,-1],"velRange":{"lo":99,"hi":127},"keyRange":{"lo":64,"hi":66},"generators":[],"sample":{"name":"Flute-D#4","start":2470780,"end":2494381,"startLoop":2483272,"endLoop":2494367,"sampleRate":32000,"originalPitch":60,"pitchCorrection":0,"sampleLink":0,"sampleType":1},"adsr":[-12000,-12000,1000,-12000]},{"sampleOffsets":[-1,-1,-1,-1],"velRange":{"lo":99,"hi":127},"keyRange":{"lo":67,"hi":69},"generators":[],"sample":{"name":"Flute-G4","start":2429944,"end":2470748,"startLoop":2458374,"endLoop":2470600,"sampleRate":32000,"originalPitch":60,"pitchCorrection":0,"sampleLink":0,"sampleType":1},"adsr":[-12000,-12000,1000,-12000]},{"sampleOffsets":[-1,-1,-1,-1],"velRange":{"lo":99,"hi":127},"keyRange":{"lo":70,"hi":72},"generators":[],"sample":{"name":"Flute-A#4","start":2399941,"end":2429912,"startLoop":2418398,"endLoop":2429744,"sampleRate":32000,"originalPitch":60,"pitchCorrection":0,"sampleLink":0,"sampleType":1},"adsr":[-12000,-12000,1000,-12000]},{"sampleOffsets":[-1,-1,-1,-1],"velRange":{"lo":99,"hi":127},"keyRange":{"lo":73,"hi":75},"generators":[],"sample":{"name":"Flute-C#5","start":2354853,"end":2399909,"startLoop":2388799,"endLoop":2399870,"sampleRate":32000,"originalPitch":60,"pitchCorrection":0,"sampleLink":0,"sampleType":1},"adsr":[-12000,-12000,1000,-12000]},{"sampleOffsets":[-1,-1,-1,-1],"velRange":{"lo":99,"hi":127},"keyRange":{"lo":76,"hi":78},"generators":[],"sample":{"name":"Flute-E5","start":2318592,"end":2354821,"startLoop":2343582,"endLoop":2354634,"sampleRate":32000,"originalPitch":60,"pitchCorrection":0,"sampleLink":0,"sampleType":1},"adsr":[-12000,-12000,1000,-12000]},{"sampleOffsets":[-1,-1,-1,-1],"velRange":{"lo":99,"hi":127},"keyRange":{"lo":79,"hi":81},"generators":[],"sample":{"name":"Flute-G5","start":2279841,"end":2318560,"startLoop":2307152,"endLoop":2318391,"sampleRate":32000,"originalPitch":60,"pitchCorrection":0,"sampleLink":0,"sampleType":1},"adsr":[-12000,-12000,1000,-12000]},{"sampleOffsets":[-1,-1,-1,-1],"velRange":{"lo":99,"hi":127},"keyRange":{"lo":82,"hi":84},"generators":[],"sample":{"name":"Flute-A#5","start":2247256,"end":2279809,"startLoop":2268677,"endLoop":2279672,"sampleRate":32000,"originalPitch":60,"pitchCorrection":0,"sampleLink":0,"sampleType":1},"adsr":[-12000,-12000,1000,-12000]},{"sampleOffsets":[-1,-1,-1,-1],"velRange":{"lo":99,"hi":127},"keyRange":{"lo":85,"hi":87},"generators":[],"sample":{"name":"Flute-C#6","start":2214685,"end":2247224,"startLoop":2241486,"endLoop":2247070,"sampleRate":32000,"originalPitch":60,"pitchCorrection":0,"sampleLink":0,"sampleType":1},"adsr":[-12000,-12000,1000,-12000]},{"sampleOffsets":[-1,-1,-1,-1],"velRange":{"lo":99,"hi":127},"keyRange":{"lo":88,"hi":90},"generators":[],"sample":{"name":"Flute-E6","start":2187596,"end":2214653,"startLoop":2202837,"endLoop":2214532,"sampleRate":32000,"originalPitch":60,"pitchCorrection":0,"sampleLink":0,"sampleType":1},"adsr":[-12000,-12000,1000,-12000]},{"sampleOffsets":[-1,-1,-1,-1],"velRange":{"lo":99,"hi":127},"keyRange":{"lo":91,"hi":94},"generators":[],"sample":{"name":"Flute-G6","start":2150346,"end":2187564,"startLoop":2175997,"endLoop":2186842,"sampleRate":32000,"originalPitch":60,"pitchCorrection":0,"sampleLink":0,"sampleType":1},"adsr":[-12000,-12000,1000,-12000]},{"sampleOffsets":[-1,-1,-1,-1],"velRange":{"lo":99,"hi":127},"keyRange":{"lo":95,"hi":123},"generators":[],"sample":{"name":"Flute-A#6","start":2117613,"end":2150314,"startLoop":2139180,"endLoop":2150148,"sampleRate":32000,"originalPitch":60,"pitchCorrection":0,"sampleLink":0,"sampleType":1},"adsr":[-12000,-12000,1000,-12000]},{"sampleOffsets":[-1,-1,-1,-1],"velRange":{"lo":75,"hi":98},"keyRange":{"lo":0,"hi":63},"generators":[],"sample":{"name":"Flute-C#4","start":2494413,"end":2524384,"startLoop":2511835,"endLoop":2524051,"sampleRate":32000,"originalPitch":60,"pitchCorrection":0,"sampleLink":0,"sampleType":1},"adsr":[1902,-12000,1000,-12000]},{"sampleOffsets":[-1,-1,-1,-1],"velRange":{"lo":75,"hi":98},"keyRange":{"lo":64,"hi":66},"generators":[],"sample":{"name":"Flute-D#4","start":2470780,"end":2494381,"startLoop":2483272,"endLoop":2494367,"sampleRate":32000,"originalPitch":60,"pitchCorrection":0,"sampleLink":0,"sampleType":1},"adsr":[1902,-12000,1000,-12000]},{"sampleOffsets":[-1,-1,-1,-1],"velRange":{"lo":75,"hi":98},"keyRange":{"lo":67,"hi":69},"generators":[],"sample":{"name":"Flute-G4","start":2429944,"end":2470748,"startLoop":2458374,"endLoop":2470600,"sampleRate":32000,"originalPitch":60,"pitchCorrection":0,"sampleLink":0,"sampleType":1},"adsr":[1902,-12000,1000,-12000]},{"sampleOffsets":[-1,-1,-1,-1],"velRange":{"lo":75,"hi":98},"keyRange":{"lo":70,"hi":72},"generators":[],"sample":{"name":"Flute-A#4","start":2399941,"end":2429912,"startLoop":2418398,"endLoop":2429744,"sampleRate":32000,"originalPitch":60,"pitchCorrection":0,"sampleLink":0,"sampleType":1},"adsr":[1902,-12000,1000,-12000]},{"sampleOffsets":[-1,-1,-1,-1],"velRange":{"lo":75,"hi":98},"keyRange":{"lo":73,"hi":75},"generators":[],"sample":{"name":"Flute-C#5","start":2354853,"end":2399909,"startLoop":2388799,"endLoop":2399870,"sampleRate":32000,"originalPitch":60,"pitchCorrection":0,"sampleLink":0,"sampleType":1},"adsr":[1902,-12000,1000,-12000]},{"sampleOffsets":[-1,-1,-1,-1],"velRange":{"lo":75,"hi":98},"keyRange":{"lo":76,"hi":78},"generators":[],"sample":{"name":"Flute-E5","start":2318592,"end":2354821,"startLoop":2343582,"endLoop":2354634,"sampleRate":32000,"originalPitch":60,"pitchCorrection":0,"sampleLink":0,"sampleType":1},"adsr":[1902,-12000,1000,-12000]},{"sampleOffsets":[-1,-1,-1,-1],"velRange":{"lo":75,"hi":98},"keyRange":{"lo":79,"hi":81},"generators":[],"sample":{"name":"Flute-G5","start":2279841,"end":2318560,"startLoop":2307152,"endLoop":2318391,"sampleRate":32000,"originalPitch":60,"pitchCorrection":0,"sampleLink":0,"sampleType":1},"adsr":[1902,-12000,1000,-12000]},{"sampleOffsets":[-1,-1,-1,-1],"velRange":{"lo":75,"hi":98},"keyRange":{"lo":82,"hi":84},"generators":[],"sample":{"name":"Flute-A#5","start":2247256,"end":2279809,"startLoop":2268677,"endLoop":2279672,"sampleRate":32000,"originalPitch":60,"pitchCorrection":0,"sampleLink":0,"sampleType":1},"adsr":[1902,-12000,1000,-12000]},{"sampleOffsets":[-1,-1,-1,-1],"velRange":{"lo":75,"hi":98},"keyRange":{"lo":85,"hi":87},"generators":[],"sample":{"name":"Flute-C#6","start":2214685,"end":2247224,"startLoop":2241486,"endLoop":2247070,"sampleRate":32000,"originalPitch":60,"pitchCorrection":0,"sampleLink":0,"sampleType":1},"adsr":[1902,-12000,1000,-12000]},{"sampleOffsets":[-1,-1,-1,-1],"velRange":{"lo":75,"hi":98},"keyRange":{"lo":88,"hi":90},"generators":[],"sample":{"name":"Flute-E6","start":2187596,"end":2214653,"startLoop":2202837,"endLoop":2214532,"sampleRate":32000,"originalPitch":60,"pitchCorrection":0,"sampleLink":0,"sampleType":1},"adsr":[1902,-12000,1000,-12000]},{"sampleOffsets":[-1,-1,-1,-1],"velRange":{"lo":75,"hi":98},"keyRange":{"lo":91,"hi":94},"generators":[],"sample":{"name":"Flute-G6","start":2150346,"end":2187564,"startLoop":2175997,"endLoop":2186842,"sampleRate":32000,"originalPitch":60,"pitchCorrection":0,"sampleLink":0,"sampleType":1},"adsr":[1902,-12000,1000,-12000]},{"sampleOffsets":[-1,-1,-1,-1],"velRange":{"lo":75,"hi":98},"keyRange":{"lo":95,"hi":123},"generators":[],"sample":{"name":"Flute-A#6","start":2117613,"end":2150314,"startLoop":2139180,"endLoop":2150148,"sampleRate":32000,"originalPitch":60,"pitchCorrection":0,"sampleLink":0,"sampleType":1},"adsr":[1902,-12000,1000,-12000]},{"sampleOffsets":[-1,-1,-1,-1],"velRange":{"lo":54,"hi":74},"keyRange":{"lo":0,"hi":63},"generators":[],"sample":{"name":"Flute-C#4","start":2494413,"end":2524384,"startLoop":2511835,"endLoop":2524051,"sampleRate":32000,"originalPitch":60,"pitchCorrection":0,"sampleLink":0,"sampleType":1},"adsr":[3102,-12000,1000,-12000]},{"sampleOffsets":[-1,-1,-1,-1],"velRange":{"lo":54,"hi":74},"keyRange":{"lo":64,"hi":66},"generators":[],"sample":{"name":"Flute-D#4","start":2470780,"end":2494381,"startLoop":2483272,"endLoop":2494367,"sampleRate":32000,"originalPitch":60,"pitchCorrection":0,"sampleLink":0,"sampleType":1},"adsr":[3102,-12000,1000,-12000]},{"sampleOffsets":[-1,-1,-1,-1],"velRange":{"lo":54,"hi":74},"keyRange":{"lo":67,"hi":69},"generators":[],"sample":{"name":"Flute-G4","start":2429944,"end":2470748,"startLoop":2458374,"endLoop":2470600,"sampleRate":32000,"originalPitch":60,"pitchCorrection":0,"sampleLink":0,"sampleType":1},"adsr":[3102,-12000,1000,-12000]},{"sampleOffsets":[-1,-1,-1,-1],"velRange":{"lo":54,"hi":74},"keyRange":{"lo":70,"hi":72},"generators":[],"sample":{"name":"Flute-A#4","start":2399941,"end":2429912,"startLoop":2418398,"endLoop":2429744,"sampleRate":32000,"originalPitch":60,"pitchCorrection":0,"sampleLink":0,"sampleType":1},"adsr":[3102,-12000,1000,-12000]},{"sampleOffsets":[-1,-1,-1,-1],"velRange":{"lo":54,"hi":74},"keyRange":{"lo":73,"hi":75},"generators":[],"sample":{"name":"Flute-C#5","start":2354853,"end":2399909,"startLoop":2388799,"endLoop":2399870,"sampleRate":32000,"originalPitch":60,"pitchCorrection":0,"sampleLink":0,"sampleType":1},"adsr":[3102,-12000,1000,-12000]},{"sampleOffsets":[-1,-1,-1,-1],"velRange":{"lo":54,"hi":74},"keyRange":{"lo":76,"hi":78},"generators":[],"sample":{"name":"Flute-E5","start":2318592,"end":2354821,"startLoop":2343582,"endLoop":2354634,"sampleRate":32000,"originalPitch":60,"pitchCorrection":0,"sampleLink":0,"sampleType":1},"adsr":[3102,-12000,1000,-12000]},{"sampleOffsets":[-1,-1,-1,-1],"velRange":{"lo":54,"hi":74},"keyRange":{"lo":79,"hi":81},"generators":[],"sample":{"name":"Flute-G5","start":2279841,"end":2318560,"startLoop":2307152,"endLoop":2318391,"sampleRate":32000,"originalPitch":60,"pitchCorrection":0,"sampleLink":0,"sampleType":1},"adsr":[3102,-12000,1000,-12000]},{"sampleOffsets":[-1,-1,-1,-1],"velRange":{"lo":54,"hi":74},"keyRange":{"lo":82,"hi":84},"generators":[],"sample":{"name":"Flute-A#5","start":2247256,"end":2279809,"startLoop":2268677,"endLoop":2279672,"sampleRate":32000,"originalPitch":60,"pitchCorrection":0,"sampleLink":0,"sampleType":1},"adsr":[3102,-12000,1000,-12000]},{"sampleOffsets":[-1,-1,-1,-1],"velRange":{"lo":54,"hi":74},"keyRange":{"lo":85,"hi":87},"generators":[],"sample":{"name":"Flute-C#6","start":2214685,"end":2247224,"startLoop":2241486,"endLoop":2247070,"sampleRate":32000,"originalPitch":60,"pitchCorrection":0,"sampleLink":0,"sampleType":1},"adsr":[3102,-12000,1000,-12000]},{"sampleOffsets":[-1,-1,-1,-1],"velRange":{"lo":54,"hi":74},"keyRange":{"lo":88,"hi":90},"generators":[],"sample":{"name":"Flute-E6","start":2187596,"end":2214653,"startLoop":2202837,"endLoop":2214532,"sampleRate":32000,"originalPitch":60,"pitchCorrection":0,"sampleLink":0,"sampleType":1},"adsr":[3102,-12000,1000,-12000]},{"sampleOffsets":[-1,-1,-1,-1],"velRange":{"lo":54,"hi":74},"keyRange":{"lo":91,"hi":94},"generators":[],"sample":{"name":"Flute-G6","start":2150346,"end":2187564,"startLoop":2175997,"endLoop":2186842,"sampleRate":32000,"originalPitch":60,"pitchCorrection":0,"sampleLink":0,"sampleType":1},"adsr":[3102,-12000,1000,-12000]},{"sampleOffsets":[-1,-1,-1,-1],"velRange":{"lo":54,"hi":74},"keyRange":{"lo":95,"hi":123},"generators":[],"sample":{"name":"Flute-A#6","start":2117613,"end":2150314,"startLoop":2139180,"endLoop":2150148,"sampleRate":32000,"originalPitch":60,"pitchCorrection":0,"sampleLink":0,"sampleType":1},"adsr":[3102,-12000,1000,-12000]},{"sampleOffsets":[-1,-1,-1,-1],"velRange":{"lo":0,"hi":53},"keyRange":{"lo":0,"hi":63},"generators":[],"sample":{"name":"Flute-C#4","start":2494413,"end":2524384,"startLoop":2511835,"endLoop":2524051,"sampleRate":32000,"originalPitch":60,"pitchCorrection":0,"sampleLink":0,"sampleType":1},"adsr":[3804,-12000,1000,-12000]},{"sampleOffsets":[-1,-1,-1,-1],"velRange":{"lo":0,"hi":53},"keyRange":{"lo":64,"hi":66},"generators":[],"sample":{"name":"Flute-D#4","start":2470780,"end":2494381,"startLoop":2483272,"endLoop":2494367,"sampleRate":32000,"originalPitch":60,"pitchCorrection":0,"sampleLink":0,"sampleType":1},"adsr":[3804,-12000,1000,-12000]},{"sampleOffsets":[-1,-1,-1,-1],"velRange":{"lo":0,"hi":53},"keyRange":{"lo":67,"hi":69},"generators":[],"sample":{"name":"Flute-G4","start":2429944,"end":2470748,"startLoop":2458374,"endLoop":2470600,"sampleRate":32000,"originalPitch":60,"pitchCorrection":0,"sampleLink":0,"sampleType":1},"adsr":[3804,-12000,1000,-12000]},{"sampleOffsets":[-1,-1,-1,-1],"velRange":{"lo":0,"hi":53},"keyRange":{"lo":70,"hi":72},"generators":[],"sample":{"name":"Flute-A#4","start":2399941,"end":2429912,"startLoop":2418398,"endLoop":2429744,"sampleRate":32000,"originalPitch":60,"pitchCorrection":0,"sampleLink":0,"sampleType":1},"adsr":[3804,-12000,1000,-12000]},{"sampleOffsets":[-1,-1,-1,-1],"velRange":{"lo":0,"hi":53},"keyRange":{"lo":73,"hi":75},"generators":[],"sample":{"name":"Flute-C#5","start":2354853,"end":2399909,"startLoop":2388799,"endLoop":2399870,"sampleRate":32000,"originalPitch":60,"pitchCorrection":0,"sampleLink":0,"sampleType":1},"adsr":[3804,-12000,1000,-12000]},{"sampleOffsets":[-1,-1,-1,-1],"velRange":{"lo":0,"hi":53},"keyRange":{"lo":76,"hi":78},"generators":[],"sample":{"name":"Flute-E5","start":2318592,"end":2354821,"startLoop":2343582,"endLoop":2354634,"sampleRate":32000,"originalPitch":60,"pitchCorrection":0,"sampleLink":0,"sampleType":1},"adsr":[3804,-12000,1000,-12000]},{"sampleOffsets":[-1,-1,-1,-1],"velRange":{"lo":0,"hi":53},"keyRange":{"lo":79,"hi":81},"generators":[],"sample":{"name":"Flute-G5","start":2279841,"end":2318560,"startLoop":2307152,"endLoop":2318391,"sampleRate":32000,"originalPitch":60,"pitchCorrection":0,"sampleLink":0,"sampleType":1},"adsr":[3804,-12000,1000,-12000]},{"sampleOffsets":[-1,-1,-1,-1],"velRange":{"lo":0,"hi":53},"keyRange":{"lo":82,"hi":84},"generators":[],"sample":{"name":"Flute-A#5","start":2247256,"end":2279809,"startLoop":2268677,"endLoop":2279672,"sampleRate":32000,"originalPitch":60,"pitchCorrection":0,"sampleLink":0,"sampleType":1},"adsr":[3804,-12000,1000,-12000]},{"sampleOffsets":[-1,-1,-1,-1],"velRange":{"lo":0,"hi":53},"keyRange":{"lo":85,"hi":87},"generators":[],"sample":{"name":"Flute-C#6","start":2214685,"end":2247224,"startLoop":2241486,"endLoop":2247070,"sampleRate":32000,"originalPitch":60,"pitchCorrection":0,"sampleLink":0,"sampleType":1},"adsr":[3804,-12000,1000,-12000]},{"sampleOffsets":[-1,-1,-1,-1],"velRange":{"lo":0,"hi":53},"keyRange":{"lo":88,"hi":90},"generators":[],"sample":{"name":"Flute-E6","start":2187596,"end":2214653,"startLoop":2202837,"endLoop":2214532,"sampleRate":32000,"originalPitch":60,"pitchCorrection":0,"sampleLink":0,"sampleType":1},"adsr":[3804,-12000,1000,-12000]},{"sampleOffsets":[-1,-1,-1,-1],"velRange":{"lo":0,"hi":53},"keyRange":{"lo":91,"hi":94},"generators":[],"sample":{"name":"Flute-G6","start":2150346,"end":2187564,"startLoop":2175997,"endLoop":2186842,"sampleRate":32000,"originalPitch":60,"pitchCorrection":0,"sampleLink":0,"sampleType":1},"adsr":[3804,-12000,1000,-12000]},{"sampleOffsets":[-1,-1,-1,-1],"velRange":{"lo":0,"hi":53},"keyRange":{"lo":95,"hi":123},"generators":[],"sample":{"name":"Flute-A#6","start":2117613,"end":2150314,"startLoop":2139180,"endLoop":2150148,"sampleRate":32000,"originalPitch":60,"pitchCorrection":0,"sampleLink":0,"sampleType":1},"adsr":[3804,-12000,1000,-12000]}]}